qndb/__init__.py
qndb/core/__init__.py
qndb/core/quantum_engine.py
qndb/core/encoding/__init__.py
qndb/core/encoding/amplitude_encoder.py
qndb/core/encoding/basis_encoder.py
qndb/core/encoding/qram.py
qndb/core/measurement/__init__.py
qndb/core/measurement/readout.py
qndb/core/measurement/statistics.py
qndb/core/operations/__init__.py
qndb/core/operations/indexing.py
qndb/core/operations/join.py
qndb/core/operations/quantum_gates.py
qndb/core/operations/search.py
qndb/core/storage/__init__.py
qndb/core/storage/circuit_compiler.py
qndb/core/storage/error_correction.py
qndb/core/storage/persistent_storage.py
qndb/distributed/__init__.py
qndb/distributed/consensus.py
qndb/distributed/node_manager.py
qndb/distributed/synchronization.py
qndb/interface/__init__.py
qndb/interface/connection_pool.py
qndb/interface/db_client.py
qndb/interface/query_language.py
qndb/interface/transaction_manager.py
qndb/middleware/__init__.py
qndb/middleware/cache.py
qndb/middleware/classical_bridge.py
qndb/middleware/optimizer.py
qndb/middleware/scheduler.py
qndb/security/__init__.py
qndb/security/access_control.py
qndb/security/audit.py
qndb/security/quantum_encryption.py
qndb/utilities/__init__.py
qndb/utilities/benchmarking.py
qndb/utilities/config.py
qndb/utilities/logging.py
qndb/utilities/visualization.py
qndb-1.0.0.dist-info/licenses/LICENSE
qndb-1.0.0.dist-info/METADATA
qndb-1.0.0.dist-info/WHEEL
qndb-1.0.0.dist-info/dependency_links.txt
qndb-1.0.0.dist-info/top_level.txt
qndb-1.0.0.dist-info/RECORD
